qiskit_quantinuum/VERSION.txt
qiskit_quantinuum/__init__.py
qiskit_quantinuum/apiconstants.py
qiskit_quantinuum/exceptions.py
qiskit_quantinuum/quantinuumbackend.py
qiskit_quantinuum/quantinuumjob.py
qiskit_quantinuum/quantinuumprovider.py
qiskit_quantinuum/version.py
qiskit_quantinuum/api/__init__.py
qiskit_quantinuum/api/exceptions.py
qiskit_quantinuum/api/quantinuumclient.py
qiskit_quantinuum/api/session.py
qiskit_quantinuum/api/rest/__init__.py
qiskit_quantinuum/api/rest/backend.py
qiskit_quantinuum/api/rest/base.py
qiskit_quantinuum/api/rest/job.py
qiskit_quantinuum/api/rest/root.py
qiskit_quantinuum/credentials/__init__.py
qiskit_quantinuum/credentials/credentials.py
qiskit_quantinuum_provider-0.4.1.dist-info/LICENSE.txt
qiskit_quantinuum_provider-0.4.1.dist-info/METADATA
qiskit_quantinuum_provider-0.4.1.dist-info/WHEEL
qiskit_quantinuum_provider-0.4.1.dist-info/top_level.txt
qiskit_quantinuum_provider-0.4.1.dist-info/RECORD
