Metadata-Version: 2.1
Name: qiskit-quantinuum-provider
Version: 0.4.1
Summary: Qiskit provider for accessing the quantum devices at Quantinuum
Home-page: https://github.com/qiskit-community/qiskit-quantinuum-provider
Author: Quantinuum
Author-email: dominic.lucchetti@quantinuum.com
License: Apache 2.0
Project-URL: Bug Tracker, https://github.com/qiskit-community/qiskit-quantinuum-provider/issues
Project-URL: Documentation, https://qiskit.org/documentation/
Project-URL: Source Code, https://github.com/qiskit-community/qiskit-quantinuum-provider
Keywords: qiskit quantum
Classifier: License :: OSI Approved :: Apache Software License
Classifier: Intended Audience :: Developers
Classifier: Intended Audience :: Science/Research
Classifier: Operating System :: OS Independent
Classifier: Operating System :: Microsoft :: Windows
Classifier: Operating System :: MacOS
Classifier: Operating System :: POSIX :: Linux
Classifier: Programming Language :: Python :: 3 :: Only
Classifier: Programming Language :: Python :: 3.8
Classifier: Programming Language :: Python :: 3.9
Classifier: Programming Language :: Python :: 3.10
Classifier: Programming Language :: Python :: 3.11
Classifier: Topic :: Scientific/Engineering
Requires-Python: >=3.8
License-File: LICENSE.txt
Requires-Dist: nest-asyncio >=1.2.0
Requires-Dist: qiskit-terra >=0.16.0
Requires-Dist: requests >=2.19
Requires-Dist: websockets >=7
Requires-Dist: pyjwt >=2.4.0
Requires-Dist: keyring >=10.6.0
Requires-Dist: pytket >=0.3.0
Requires-Dist: pytket-quantinuum >=0.9.0
